LavaBusiness/AioLava.py
LavaBusiness/__init__.py
LavaBusiness/processors/__init__.py
LavaBusiness/processors/response_processors.py
LavaBusiness/types/__init__.py
LavaBusiness/types/client.py
LavaBusiness/types/errors.py
LavaBusiness/types/models.py
lavabusiness-2.0.0.dist-info/licenses/LICENSE
lavabusiness-2.0.0.dist-info/METADATA
lavabusiness-2.0.0.dist-info/WHEEL
lavabusiness-2.0.0.dist-info/top_level.txt
lavabusiness-2.0.0.dist-info/RECORD
