Metadata-Version: 2.4
Name: LavaBusiness
Version: 2.0.0
Summary: Async client for lava.ru business-API
Home-page: https://github.com/lztrox/LavaBusiness
Author: lztrox
Project-URL: Docs, https://lavabusiness.readthedocs.io/ru/latest/
Project-URL: Source code, https://github.com/lztrox/LavaBusiness
Project-URL: Author, https://github.com/lztrox
Classifier: Development Status :: 5 - Production/Stable
Classifier: License :: OSI Approved :: Mozilla Public License 2.0 (MPL 2.0)
Classifier: Framework :: AsyncIO
Classifier: Programming Language :: Python :: 3.7
Classifier: Programming Language :: Python :: 3.8
Classifier: Programming Language :: Python :: 3.9
Classifier: Programming Language :: Python :: 3.10
Classifier: Programming Language :: Python :: 3.11
Classifier: Programming Language :: Python :: 3.12
Requires-Python: >=3.7
License-File: LICENSE
Requires-Dist: aiohttp>=3.7.0
Requires-Dist: pydantic>=1.8.0
Dynamic: author
Dynamic: classifier
Dynamic: description
Dynamic: description-content-type
Dynamic: home-page
Dynamic: license-file
Dynamic: project-url
Dynamic: requires-dist
Dynamic: requires-python
Dynamic: summary
